PhysiqueUtils/__init__.py
PhysiqueUtils/main.py
PhysiqueUtils/plot.py
physiqueutils-0.1.0.dist-info/METADATA
physiqueutils-0.1.0.dist-info/WHEEL
physiqueutils-0.1.0.dist-info/top_level.txt
physiqueutils-0.1.0.dist-info/RECORD
