Metadata-Version: 2.4
Name: physiqueUtils
Version: 0.1.0
Summary: Une librairie pour les TP de physique, gérant les unités, les incertitudes et les graphiques.
Author-email: LE BIHAN Alwin <alwinlebihan@gmail.com>
Classifier: Programming Language :: Python :: 3
Classifier: License :: OSI Approved :: MIT License
Classifier: Operating System :: OS Independent
Requires-Python: >=3.8
Requires-Dist: numpy
Requires-Dist: matplotlib
Requires-Dist: uncertainties
Requires-Dist: scipy
Requires-Dist: pint
